{
  "project_info": {
    "project_number": "924840418511",
    "project_id": "mobileprogramming-7ec3c",
    "storage_bucket": "mobileprogramming-7ec3c.appspot.com"
  },
  "client": [
    {
      "client_info": {
        "mobilesdk_app_id": "1:924840418511:android:387cc412cb4e1cd1c1abba",
        "android_client_info": {
          "package_name": "com.example.mp_firebase"
        }
      },
      "oauth_client": [],
      "api_key": [
        {
          "current_key": "AIzaSyAWCvTgBaB06wL9citNFDLBxU8_-9SPwrQ"
        }
      ],
      "services": {
        "appinvite_service": {
          "other_platform_oauth_client": []
        }
      }
    }
  ],
  "configuration_version": "1"
}